__init__.py
cli.py
core.py
yoloprep-0.0.1.dist-info/licenses/LICENSE
yoloprep-0.0.1.dist-info/METADATA
yoloprep-0.0.1.dist-info/WHEEL
yoloprep-0.0.1.dist-info/top_level.txt
yoloprep-0.0.1.dist-info/RECORD
