Metadata-Version: 2.4
Name: yoloprep
Version: 0.0.1
Summary: Prepare Your Dataset for YOLO the Right Way
Author-email: Kalinin Mitko <kalinin.mitko@gmail.com>
License: MIT License
Project-URL: Homepage, https://github.com/null-none/yoloprep
Keywords: yolo,dataset,preparation,computer vision,deep learning
Classifier: License :: OSI Approved :: MIT License
Classifier: Programming Language :: Python
Classifier: Programming Language :: Python :: 3
Requires-Python: >=3.9
License-File: LICENSE
Provides-Extra: dev
Requires-Dist: pip-tools; extra == "dev"
Dynamic: license-file
